dotnest/__init__.py
dotnest/tests/test_dotnest.py
dotnest-1.1.dist-info/METADATA
dotnest-1.1.dist-info/WHEEL
dotnest-1.1.dist-info/licenses/LICENSE
dotnest-1.1.dist-info/RECORD
