Metadata-Version: 2.3
Name: dotnest
Version: 1.1
Summary: A library for accessing deep structures from simple text statements
Project-URL: Homepage, https://github.com/hardaker/dotnest/
Author-email: Wes Hardaker <opensource@hardakers.net>
License-Expression: MIT
License-File: LICENSE
Classifier: Operating System :: OS Independent
Classifier: Programming Language :: Python :: 3
Requires-Python: >=3.7
